{"summaries":[{"symbol":{"__symbol":0,"members":[]},"metadata":{"__symbolic":"class","members":{"__ctor__":[{"__symbolic":"constructor","parameters":[{"__symbol":1,"members":[]},{"__symbol":2,"members":[]},{"__symbol":3,"members":[]}]}],"ngOnInit":[{"__symbolic":"method"}],"pesquisar":[{"__symbolic":"method"}],"select":[{"__symbolic":"method"}],"close":[{"__symbolic":"method"}],"sw":[{"__symbolic":"method"}],"salvar":[{"__symbolic":"method"}]}},"type":{"summaryKind":1,"type":{"reference":{"__symbol":0,"members":[]},"diDeps":[{"isAttribute":false,"isHost":false,"isSelf":false,"isSkipSelf":false,"isOptional":false,"token":{"identifier":{"reference":{"__symbol":6,"members":[]}}}},{"isAttribute":false,"isHost":false,"isSelf":false,"isSkipSelf":false,"isOptional":false,"token":{"identifier":{"reference":{"__symbol":2,"members":[]}}}},{"isAttribute":false,"isHost":false,"isSelf":false,"isSkipSelf":false,"isOptional":false,"token":{"identifier":{"reference":{"__symbol":7,"members":[]}}}}],"lifecycleHooks":[0]},"isComponent":true,"selector":"jhi-assistente","exportAs":null,"inputs":{},"outputs":{},"hostListeners":{},"hostProperties":{},"hostAttributes":{},"providers":[],"viewProviders":[],"queries":[],"viewQueries":[],"entryComponents":[],"changeDetection":1,"template":{"animations":[],"ngContentSelectors":[],"encapsulation":0},"componentViewType":{"__symbol":8,"members":[]},"rendererType":{"__symbol":9,"members":[]},"componentFactory":{"__symbol":10,"members":[]}}},{"symbol":{"__symbol":4,"members":[]},"metadata":{"__symbolic":"class","members":{"__ctor__":[{"__symbolic":"constructor","parameters":[{"__symbol":5,"members":[]}]}],"ngOnInit":[{"__symbolic":"method"}]}},"type":{"summaryKind":1,"type":{"reference":{"__symbol":4,"members":[]},"diDeps":[{"isAttribute":false,"isHost":false,"isSelf":false,"isSkipSelf":false,"isOptional":false,"token":{"identifier":{"reference":{"__symbol":5,"members":[]}}}}],"lifecycleHooks":[0]},"isComponent":true,"selector":"jhi-impressora-assistent-popup","exportAs":null,"inputs":{},"outputs":{},"hostListeners":{},"hostProperties":{},"hostAttributes":{},"providers":[],"viewProviders":[],"queries":[],"viewQueries":[],"entryComponents":[],"changeDetection":1,"template":{"animations":[],"ngContentSelectors":[],"encapsulation":2},"componentViewType":{"__symbol":11,"members":[]},"rendererType":{"__symbol":12,"members":[]},"componentFactory":{"__symbol":13,"members":[]}}}],"symbols":[{"__symbol":0,"name":"AssistenteComponent","filePath":"/home/mfernandes/erestaurante/src/main/webapp/app/entities/impressora/assistente/assistente.component.d.ts"},{"__symbol":1,"name":"NgbActiveModal","filePath":"/home/mfernandes/erestaurante/node_modules/@ng-bootstrap/ng-bootstrap/index.d.ts"},{"__symbol":2,"name":"ImpressoraService","filePath":"/home/mfernandes/erestaurante/src/main/webapp/app/entities/impressora/impressora.service.d.ts"},{"__symbol":3,"name":"JhiEventManager","filePath":"/home/mfernandes/erestaurante/node_modules/ng-jhipster/index.d.ts"},{"__symbol":4,"name":"ImpressoraAssistentePopupComponent","filePath":"/home/mfernandes/erestaurante/src/main/webapp/app/entities/impressora/assistente/assistente.component.d.ts"},{"__symbol":5,"name":"ImpressoraPopupService","filePath":"/home/mfernandes/erestaurante/src/main/webapp/app/entities/impressora/impressora-popup.service.d.ts"},{"__symbol":6,"name":"NgbActiveModal","filePath":"/home/mfernandes/erestaurante/node_modules/@ng-bootstrap/ng-bootstrap/modal/modal-ref.d.ts"},{"__symbol":7,"name":"JhiEventManager","filePath":"/home/mfernandes/erestaurante/node_modules/ng-jhipster/src/service/event-manager.service.d.ts"},{"__symbol":8,"name":"View_AssistenteComponent_0","filePath":"/home/mfernandes/erestaurante/src/main/webapp/app/entities/impressora/assistente/assistente.component.ngfactory.d.ts"},{"__symbol":9,"name":"RenderType_AssistenteComponent","filePath":"/home/mfernandes/erestaurante/src/main/webapp/app/entities/impressora/assistente/assistente.component.ngfactory.d.ts"},{"__symbol":10,"name":"AssistenteComponentNgFactory","filePath":"/home/mfernandes/erestaurante/src/main/webapp/app/entities/impressora/assistente/assistente.component.ngfactory.d.ts"},{"__symbol":11,"name":"View_ImpressoraAssistentePopupComponent_0","filePath":"/home/mfernandes/erestaurante/src/main/webapp/app/entities/impressora/assistente/assistente.component.ngfactory.d.ts"},{"__symbol":12,"name":"RenderType_ImpressoraAssistentePopupComponent","filePath":"/home/mfernandes/erestaurante/src/main/webapp/app/entities/impressora/assistente/assistente.component.ngfactory.d.ts"},{"__symbol":13,"name":"ImpressoraAssistentePopupComponentNgFactory","filePath":"/home/mfernandes/erestaurante/src/main/webapp/app/entities/impressora/assistente/assistente.component.ngfactory.d.ts"}]}